efficient/LoggingFactory.py
efficient/ThreadExecutor.py
efficient/__init__.py
efficient/tools_date.py
efficient/tools_dict.py
efficient/tools_function.py
efficient/tools_hash.py
efficient/tools_json.py
efficient/tools_list.py
efficient/tools_math.py
efficient/tools_url_parse.py
efficient-1.4.9.dist-info/METADATA
efficient-1.4.9.dist-info/WHEEL
efficient-1.4.9.dist-info/top_level.txt
efficient-1.4.9.dist-info/RECORD
