Metadata-Version: 2.4
Name: efficient
Version: 1.4.9
Summary: 效率提升
Home-page: https://gitee.com/jaifire/efficient
Author: jaifire
Author-email: boydearea@163.com
Classifier: Programming Language :: Python :: 3
Classifier: License :: OSI Approved :: MIT License
Classifier: Operating System :: OS Independent
Requires-Python: >=3.6
Dynamic: author
Dynamic: author-email
Dynamic: classifier
Dynamic: description
Dynamic: home-page
Dynamic: requires-python
Dynamic: summary
